otaku_info/Config.py
otaku_info/__init__.py
otaku_info/enums.py
otaku_info/main.py
otaku_info/mappings.py
otaku_info/template_extras.py
otaku_info/background/__init__.py
otaku_info/background/anilist.py
otaku_info/background/anilist_manga_chapter_guesses.py
otaku_info/background/ln_releases.py
otaku_info/background/mangadex.py
otaku_info/background/notifications.py
otaku_info/db/LnRelease.py
otaku_info/db/MangaChapterGuess.py
otaku_info/db/MediaIdMapping.py
otaku_info/db/MediaItem.py
otaku_info/db/MediaList.py
otaku_info/db/MediaListItem.py
otaku_info/db/MediaNotification.py
otaku_info/db/MediaUserState.py
otaku_info/db/NotificationSetting.py
otaku_info/db/ServiceUsername.py
otaku_info/db/__init__.py
otaku_info/external/__init__.py
otaku_info/external/anilist.py
otaku_info/external/mangadex.py
otaku_info/external/myanimelist.py
otaku_info/external/reddit.py
otaku_info/external/entities/AnilistItem.py
otaku_info/external/entities/AnilistUserItem.py
otaku_info/external/entities/AnimeListItem.py
otaku_info/external/entities/MangadexItem.py
otaku_info/external/entities/MyanimelistItem.py
otaku_info/external/entities/RedditLnRelease.py
otaku_info/external/entities/__init__.py
otaku_info/routes/__init__.py
otaku_info/routes/external_service.py
otaku_info/routes/ln.py
otaku_info/routes/media.py
otaku_info/routes/notifications.py
otaku_info/routes/schedule.py
otaku_info/routes/updates.py
otaku_info/routes/api/__init__.py
otaku_info/routes/api/media_api.py
otaku_info/test/TestFramework.py
otaku_info/test/__init__.py
otaku_info/test/external/TestAnilist.py
otaku_info/test/external/TestMangadex.py
otaku_info/test/external/TestMyanimelist.py
otaku_info/test/external/TestReddit.py
otaku_info/test/external/__init__.py
otaku_info/test/misc/TestApiCalls.py
otaku_info/test/misc/TestConfig.py
otaku_info/test/misc/TestErrorHandling.py
otaku_info/test/misc/TestMappings.py
otaku_info/test/misc/TestServer.py
otaku_info/test/misc/__init__.py
otaku_info/test/routes/TestForgotRoute.py
otaku_info-0.6.2.dist-info/LICENSE
otaku_info-0.6.2.dist-info/METADATA
otaku_info-0.6.2.dist-info/WHEEL
otaku_info-0.6.2.dist-info/top_level.txt
otaku_info-0.6.2.dist-info/RECORD
