Metadata-Version: 2.1
Name: otaku-info
Version: 0.6.2
Summary: Website providing information on Japanese entertainment media
Home-page: https://gitlab.namibsun.net/namibsun/python/otaku-info
Author: Hermann Krumrey
Author-email: hermann@krumreyh.com
License: GNU GPL3
Platform: UNKNOWN
Classifier: License :: OSI Approved :: GNU General Public License v3 (GPLv3)
License-File: LICENSE
Requires-Dist: Flask
Requires-Dist: werkzeug
Requires-Dist: flask-sqlalchemy
Requires-Dist: flask-login
Requires-Dist: puffotter[crypto]
Requires-Dist: requests
Requires-Dist: sqlalchemy (==1.3.19)
Requires-Dist: bokkichat
Requires-Dist: beautifulsoup4
Requires-Dist: jerrycan
